odoo/addons/web_m2x_options/README.rst
odoo/addons/web_m2x_options/__init__.py
odoo/addons/web_m2x_options/__manifest__.py
odoo/addons/web_m2x_options/i18n/ar.po
odoo/addons/web_m2x_options/i18n/de.po
odoo/addons/web_m2x_options/i18n/es.po
odoo/addons/web_m2x_options/i18n/es_BO.po
odoo/addons/web_m2x_options/i18n/fi.po
odoo/addons/web_m2x_options/i18n/fr.po
odoo/addons/web_m2x_options/i18n/hr.po
odoo/addons/web_m2x_options/i18n/it.po
odoo/addons/web_m2x_options/i18n/ja.po
odoo/addons/web_m2x_options/i18n/nl.po
odoo/addons/web_m2x_options/i18n/nl_NL.po
odoo/addons/web_m2x_options/i18n/pt_BR.po
odoo/addons/web_m2x_options/i18n/sl.po
odoo/addons/web_m2x_options/i18n/tr.po
odoo/addons/web_m2x_options/i18n/web_m2x_options.pot
odoo/addons/web_m2x_options/i18n/zh_CN.po
odoo/addons/web_m2x_options/models/__init__.py
odoo/addons/web_m2x_options/models/ir_config_parameter.py
odoo/addons/web_m2x_options/models/ir_http.py
odoo/addons/web_m2x_options/readme/CONTRIBUTORS.md
odoo/addons/web_m2x_options/readme/CREDITS.md
odoo/addons/web_m2x_options/readme/DESCRIPTION.md
odoo/addons/web_m2x_options/readme/ROADMAP.md
odoo/addons/web_m2x_options/readme/USAGE.md
odoo/addons/web_m2x_options/static/description/icon.png
odoo/addons/web_m2x_options/static/description/index.html
odoo/addons/web_m2x_options/static/src/components/base.xml
odoo/addons/web_m2x_options/static/src/components/form.esm.js
odoo/addons/web_m2x_options/static/src/views/fields/standard_field_props.esm.js
odoo/addons/web_m2x_options/tests/__init__.py
odoo/addons/web_m2x_options/tests/test_ir_config_parameter.py
odoo_addon_web_m2x_options-18.0.1.0.1.2.dist-info/METADATA
odoo_addon_web_m2x_options-18.0.1.0.1.2.dist-info/WHEEL
odoo_addon_web_m2x_options-18.0.1.0.1.2.dist-info/top_level.txt
odoo_addon_web_m2x_options-18.0.1.0.1.2.dist-info/RECORD
