Metadata-Version: 2.1
Name: odoo-addon-web_m2x_options
Version: 18.0.1.0.1.2
Requires-Python: >=3.10
Requires-Dist: odoo==18.0.*
Summary: web_m2x_options
Home-page: https://github.com/OCA/web
License: AGPL-3
Author: initOS GmbH,ACSONE SA/NV, 0k.io, Tecnativa, Sygel, Odoo Community Association (OCA)
Author-email: support@odoo-community.org
Classifier: Programming Language :: Python
Classifier: Framework :: Odoo
Classifier: Framework :: Odoo :: 18.0
Classifier: License :: OSI Approved :: GNU Affero General Public License v3
